[{"idInBook":1,"hadithNumber":15660,"arabic":"حدثنا عفان، حدثنا يحيى بن سعيد، عن أبي جعفر الخطمي، قال: حدثنا عمارة بن خزيمة، والحارث بن فضيل، عن عبد الرحمن بن أبي قراد، قال: \" خرجت مع النبي صلى الله عليه وسلم حاجا، فرأيته خرج من الخلاء، فاتبعته بالإداوة - أو القدح - فجلست له بالطريق وكان إذا أتى حاجته أبعد \" (2)","english":{"narrator":"","text":""}},{"idInBook":2,"hadithNumber":15661,"arabic":"حدثنا عفان، حدثنا يحيى بن سعيد، قال: حدثني أبو جعفر عمير بن يزيد، قال: حدثني الحارث بن فضيل، وعمارة بن خزيمة بن ثابت، عن عبد الرحمن بن أبي قراد، قال: خرجت مع رسول الله صلى الله عليه وسلم حاجا، قال: فنزل منزلا وخرج من الخلاء، فاتبعته بالإداوة - أو القدح - وكان رسول الله صلى الله عليه وسلم إذا أراد حاجة أبعد، فجلست له بالطريق حتى انصرف رسول الله صلى الله عليه وسلم، فقلت له: يا رسول الله، الوضوء. \" فأقبل رسول الله صلى الله عليه وسلم إلي فصب رسول الله صلى الله عليه وسلم على يده، فغسلها، ثم أدخل يده فكفها، فصب على يده واحدة، ثم ms2845 مسح على رأسه، ثم قبض الماء قبضا بيده، فضرب به على ظهر قدمه، فمسح بيده على قدمه، ثم جاء فصلى لنا الظهر \" (1)","english":{"narrator":"","text":""}}]