[{"idInBook":1,"hadithNumber":82,"arabic":"حدثنا عبد الرحمن بن مهدي، عن سفيان، عن أبي إسحاق، عن حارثة، قال:","english":{"narrator":"","text":""},"grade":"Hasan"},{"idInBook":2,"hadithNumber":83,"arabic":"حدثنا محمد بن جعفر، قال: حدثنا شعبة، عن الحكم، عن أبي وائل:","english":{"narrator":"","text":""},"grade":"Sahih"},{"idInBook":3,"hadithNumber":84,"arabic":"حدثنا عفان، حدثنا شعبة، عن أبي إسحاق، قال: سمعت عمرو بن ميمون، قال:","english":{"narrator":"","text":""},"grade":"Sahih"},{"idInBook":4,"hadithNumber":85,"arabic":"حدثنا عفان، حدثنا عبد الواحد بن زياد، قال: حدثنا عاصم بن كليب، قال:","english":{"narrator":"","text":""},"grade":"Sahih"},{"idInBook":5,"hadithNumber":86,"arabic":"حدثنا محمد بن جعفر، حدثنا شعبة، قال: سمعت عاصم بن عمرو البجلي، يحدث","english":{"narrator":"","text":""},"grade":"Sahih"},{"idInBook":6,"hadithNumber":87,"arabic":"حدثنا قتيبة بن سعيد، حدثنا ابن لهيعة، عن أبي النضر، عن أبي سلمة","english":{"narrator":"","text":""},"grade":"Da'if"},{"idInBook":7,"hadithNumber":88,"arabic":"حدثنا هارون بن معروف، قال: حدثنا ابن وهب، عن عمرو بن الحارث، عن أبي النضر، عن أبي سلمة بن عبد الرحمن، عن عبد الله بن عمر","english":{"narrator":"","text":""},"grade":"Hasan"},{"idInBook":8,"hadithNumber":89,"arabic":"حدثنا عفان، حدثنا همام بن يحيى، قال: حدثنا قتادة، عن سالم بن أبي الجعد الغطفاني، عن معدان (3) بن أبي طلحة اليعمري:","english":{"narrator":"","text":""},"grade":"Sahih"},{"idInBook":9,"hadithNumber":90,"arabic":"حدثنا يعقوب، حدثنا أبي، عن ابن إسحاق، قال: حدثني نافع مولى عبد الله بن عمر","english":{"narrator":"","text":""},"grade":"Sahih"},{"idInBook":10,"hadithNumber":91,"arabic":"حدثنا حسن بن موسى، وحسين بن محمد، قالا: حدثنا شيبان، عن يحيى، عن أبي سلمة، عن أبي هريرة:","english":{"narrator":"","text":""},"grade":"Hasan"},{"idInBook":11,"hadithNumber":92,"arabic":"حدثنا حسن بن موسى، قال: حدثنا زهير، قال: حدثنا عاصم الأحول، عن أبي عثمان، قال:","english":{"narrator":"","text":""},"grade":"Sahih"},{"idInBook":12,"hadithNumber":93,"arabic":"حدثنا حسن، قال: حدثنا ابن لهيعة، حدثنا أبو الأسود (2) ، أنه سمع محمد بن عبد الرحمن ابن لبيبة يحدث","english":{"narrator":"","text":""},"grade":"Sahih"},{"idInBook":13,"hadithNumber":94,"arabic":"حدثنا يعقوب، حدثنا أبي، عن ابن إسحاق، حدثني نافع، عن عبد الله بن عمر","english":{"narrator":"","text":""},"grade":"Da'if"},{"idInBook":14,"hadithNumber":95,"arabic":"حدثنا يعقوب، حدثنا أبي، عن ابن إسحاق، حدثني الزهري، عن عبيد الله بن عبد الله بن عتبة بن مسعود، عن عبد الله بن عباس، قال:","english":{"narrator":"","text":""},"grade":"Hasan"},{"idInBook":15,"hadithNumber":96,"arabic":"حدثنا يعقوب، حدثنا أبي، عن ابن إسحاق، كما حدثني عنه نافع مولاه، قال:","english":{"narrator":"","text":""},"grade":"Hasan"},{"idInBook":16,"hadithNumber":97,"arabic":"حدثنا مؤمل، حدثنا حماد، قال: حدثنا زياد بن مخراق، عن شهر، عن عقبة بن عامر، قال:","english":{"narrator":"","text":""},"grade":"Hasan"},{"idInBook":17,"hadithNumber":98,"arabic":"حدثنا أسود بن عامر، قال: أخبرنا (1) جعفر - يعني الأحمر - عن مطرف، عن الحكم، عن مجاهد، قال:","english":{"narrator":"","text":""},"grade":"Hasan"},{"idInBook":18,"hadithNumber":99,"arabic":"حدثنا أسود بن عامر، قال: حدثنا زهير، عن سليمان الأعمش، حدثنا (3) إبراهيم، عن عابس بن ربيعة، قال:","english":{"narrator":"","text":""},"grade":"Hasan"},{"idInBook":19,"hadithNumber":100,"arabic":"حدثنا أبو اليمان، قال: أخبرنا (1) شعيب، عن الزهري، قال: أخبرنا السائب بن يزيد ابن أخت نمر، أن حويطب بن عبد العزى أخبره","english":{"narrator":"","text":""},"grade":"Sahih"},{"idInBook":20,"hadithNumber":101,"arabic":"حدثنا سكن بن نافع الباهلي، قال: حدثنا صالح، عن الزهري، قال: حدثني ربيعة بن دراج:","english":{"narrator":"","text":""},"grade":"Sahih"},{"idInBook":21,"hadithNumber":102,"arabic":"حدثنا محمد بن يزيد، حدثنا ms0032 محمد بن إسحاق، قال: حدثنا العلاء بن عبد الرحمن بن يعقوب، عن رجل من قريش من بني سهم","english":{"narrator":"","text":""},"grade":"Da'if"},{"idInBook":22,"hadithNumber":103,"arabic":"حدثنا يعقوب، حدثنا أبي، عن ابن إسحاق، قال: وحدثني العلاء بن عبد الرحمن، عن رجل من بني سهم","english":{"narrator":"","text":""},"grade":"Da'if"},{"idInBook":23,"hadithNumber":104,"arabic":"حدثنا عبيدة بن حميد، عن داود بن أبي هند، عن أبي نضرة، عن أبي سعيد، قال:","english":{"narrator":"","text":""},"grade":"Da'if"},{"idInBook":24,"hadithNumber":105,"arabic":"حدثنا عبيدة بن حميد، حدثني عبيد الله بن عمر، عن نافع، عن ابن عمر","english":{"narrator":"","text":""},"grade":"Sahih"},{"idInBook":25,"hadithNumber":106,"arabic":"حدثنا الحسن بن يحيى، قال: أخبرنا (2) ابن المبارك، قال: حدثنا معمر، عن الزهري، عن ربيعة بن دراج:","english":{"narrator":"","text":""},"grade":"Sahih"},{"idInBook":26,"hadithNumber":107,"arabic":"حدثنا أبو المغيرة، حدثنا صفوان، حدثنا شريح بن عبيد (4) ، قال:","english":{"narrator":"","text":""},"grade":"Da'if"},{"idInBook":27,"hadithNumber":108,"arabic":"حدثنا أبو المغيرة، وعصام بن خالد، قالا: حدثنا صفوان، عن شريح بن عبيد (2) وراشد بن سعد، وغيرهما، قالوا:","english":{"narrator":"","text":""},"grade":"Da'if"},{"idInBook":28,"hadithNumber":109,"arabic":"حدثنا أبو المغيرة، حدثنا ابن عياش، قال: حدثني الأوزاعي وغيره، عن الزهري، عن سعيد بن المسيب","english":{"narrator":"","text":""},"grade":"Hasan"},{"idInBook":29,"hadithNumber":110,"arabic":"حدثنا بهز، حدثنا أبان، عن قتادة، عن أبى العالية","english":{"narrator":"","text":""},"grade":"Da'if"},{"idInBook":30,"hadithNumber":111,"arabic":"حدثنا أبو المغيرة، حدثنا صفوان، حدثنا عبد الرحمن بن جبير بن نفير","english":{"narrator":"","text":""},"grade":"Sahih"},{"idInBook":31,"hadithNumber":112,"arabic":"حدثنا بشر بن شعيب بن أبي حمزة، قال: حدثني أبي، عن الزهري، قال: أخبرني سالم بن عبد الله، أن عبد الله بن عمر","english":{"narrator":"","text":""},"grade":"Hasan"},{"idInBook":32,"hadithNumber":113,"arabic":"حدثنا أبو اليمان، حدثنا أبو بكر بن عبد الله، عن راشد بن سعد","english":{"narrator":"","text":""},"grade":"Sahih"},{"idInBook":33,"hadithNumber":114,"arabic":"حدثنا علي بن إسحاق، أخبرنا عبد الله - يعني ابن المبارك - أخبرنا محمد بن سوقة، عن عبد الله بن دينار، عن ابن عمر","english":{"narrator":"","text":""},"grade":"Sahih"},{"idInBook":34,"hadithNumber":115,"arabic":"حدثنا أبو اليمان، حدثنا أبو بكر، عن حكيم بن عمير (2) وضمرة بن حبيب، قالا:","english":{"narrator":"","text":""},"grade":"Sahih"},{"idInBook":35,"hadithNumber":116,"arabic":"حدثنا أبو سعيد مولى بني هاشم، قال: حدثنا زائدة، حدثنا سماك، عن عكرمة، عن ابن عباس، قال:","english":{"narrator":"","text":""},"grade":"Da'if"},{"idInBook":36,"hadithNumber":117,"arabic":"حدثنا عصام (2) بن خالد، وأبو اليمان، قالا: أخبرنا شعيب بن أبي حمزة، عن الزهري، قال: حدثنا عبيد الله بن عبد الله بن عتبة بن مسعود","english":{"narrator":"","text":""},"grade":"Sahih"},{"idInBook":37,"hadithNumber":118,"arabic":"حدثنا أبو المغيرة، حدثنا الأوزاعي، حدثنا عمرو بن شعيب، عن عبد الله بن عمرو بن العاص","english":{"narrator":"","text":""},"grade":"Sahih"},{"idInBook":38,"hadithNumber":119,"arabic":"حدثنا الحكم بن نافع، حدثنا ابن عياش، عن أبي سبأ عتبة بن تميم، عن الوليد بن عامر اليزني، عن عروة بن مغيث (3) الأنصاري","english":{"narrator":"","text":""},"grade":"Sahih"},{"idInBook":39,"hadithNumber":120,"arabic":"حدثنا أبو اليمان الحكم بن نافع، حدثنا أبو بكر بن عبد الله، عن راشد بن سعد، عن حمرة (2) بن عبد كلال، قال:","english":{"narrator":"","text":""},"grade":"Hasan"},{"idInBook":40,"hadithNumber":121,"arabic":"حدثنا عبد الله بن يزيد، حدثنا حيوة، أخبرنا أبو عقيل، عن ابن عمه","english":{"narrator":"","text":""},"grade":"Da'if"},{"idInBook":41,"hadithNumber":122,"arabic":"حدثنا سليمان بن داود - يعني أبا داود الطيالسي - قال: حدثنا أبو عوانة، عن داود الأودي، عن عبد الرحمن المسلي","english":{"narrator":"","text":""},"grade":"Sahih"},{"idInBook":42,"hadithNumber":123,"arabic":"حدثنا عبد الصمد، حدثني أبي، حدثنا يزيد - يعني الرشك - عن","english":{"narrator":"","text":""},"grade":"Da'if"},{"idInBook":43,"hadithNumber":124,"arabic":"حدثنا يحيى بن إسحاق، حدثنا ابن لهيعة، عن أبي الزبير، عن جابر، قال:","english":{"narrator":"","text":""},"grade":"Sahih"},{"idInBook":44,"hadithNumber":125,"arabic":"حدثنا هارون، حدثنا ابن وهب، حدثني عمرو بن الحارث، أن عمر بن السائب حدثه، أن القاسم بن أبي القاسم السبائي حدثه، عن قاص الأجناد بالقسطنطينية، أنه سمعه يحدث","english":{"narrator":"","text":""},"grade":"Hasan"},{"idInBook":45,"hadithNumber":126,"arabic":"حدثنا أبو سلمة الخزاعي، أخبرنا ليث، ويونس، حدثنا ليث، عن يزيد بن عبد الله بن أسامة بن الهاد، عن الوليد بن أبي الوليد، عن عثمان بن عبد الله - يعني ابن سراقة -","english":{"narrator":"","text":""},"grade":"Hasan"},{"idInBook":46,"hadithNumber":127,"arabic":"حدثنا عفان، حدثنا أبو عوانة، عن سليمان الأعمش، عن شقيق، عن سلمان (1) بن ربيعة، قال:","english":{"narrator":"","text":""},"grade":"Sahih"},{"idInBook":47,"hadithNumber":128,"arabic":"حدثنا عفان، حدثنا خالد، عن يزيد بن أبي زياد، عن عاصم بن عبيد الله، عن أبيه، أو عن جده (5) .","english":{"narrator":"","text":""},"grade":"Sahih"},{"idInBook":48,"hadithNumber":129,"arabic":"حدثنا عفان، حدثنا حماد بن سلمة، عن علي بن زيد، عن أبي رافع:","english":{"narrator":"","text":""},"grade":"Sahih"},{"idInBook":49,"hadithNumber":130,"arabic":"حدثنا عفان، حدثنا همام، حدثنا قتادة، حدثني أبو العالية","english":{"narrator":"","text":""},"grade":"Da'if"},{"idInBook":50,"hadithNumber":131,"arabic":"حدثنا عفان، حدثنا وهيب، حدثنا عبد الله بن عثمان بن خثيم (3) ، عن سعيد بن جبير، عن ابن عباس","english":{"narrator":"","text":""},"grade":"Sahih"},{"idInBook":51,"hadithNumber":132,"arabic":"حدثنا عفان، حدثنا حماد، أخبرنا عمار بن أبي عمار (2)","english":{"narrator":"","text":""},"grade":"Sahih"},{"idInBook":52,"hadithNumber":133,"arabic":"حدثنا معاوية بن عمرو، حدثنا زائدة، حدثنا عاصم. وحسين بن علي، عن زائدة، عن عاصم، عن زر، عن عبد الله، قال:","english":{"narrator":"","text":""},"grade":"Hasan"},{"idInBook":53,"hadithNumber":134,"arabic":"حدثنا موسى بن داود، حدثنا ابن لهيعة، عن أبي الزبير، عن جابر","english":{"narrator":"","text":""},"grade":"Hasan"},{"idInBook":54,"hadithNumber":135,"arabic":"حدثنا أبو سعيد مولى بني هاشم، حدثنا الهيثم بن رافع الطاطري (2) بصري، حدثني أبو يحيى، رجل من أهل مكة، عن فروخ، مولى عثمان:","english":{"narrator":"","text":""},"grade":"Sahih"},{"idInBook":55,"hadithNumber":136,"arabic":"حدثنا أبو اليمان، أخبرنا شعيب، عن الزهري، حدثنا سالم بن عبد الله، أن عبد الله بن عمر، قال:","english":{"narrator":"","text":""},"grade":"Da'if"},{"idInBook":56,"hadithNumber":137,"arabic":"حدثنا هارون، حدثنا ابن وهب، أخبرني يونس، عن ابن شهاب، عن سالم، عن أبيه، قال:","english":{"narrator":"","text":""},"grade":"Sahih"},{"idInBook":57,"hadithNumber":138,"arabic":"حدثنا حجاج، حدثنا ليث، حدثني بكير، عن عبد الملك بن سعيد الأنصاري، عن جابر بن عبد الله","english":{"narrator":"","text":""},"grade":"Sahih"},{"idInBook":58,"hadithNumber":139,"arabic":"حدثنا يونس بن محمد، حدثنا داود - يعني ابن أبي الفرات - عن عبد الله بن بريدة","english":{"narrator":"","text":""},"grade":"Sahih"},{"idInBook":59,"hadithNumber":140,"arabic":"حدثنا أبو سعيد، حدثنا ابن لهيعة، حدثنا بكير، عن سعيد بن المسيب","english":{"narrator":"","text":""},"grade":"Sahih"},{"idInBook":60,"hadithNumber":141,"arabic":"حدثنا أبو سعيد مولى بني هاشم، حدثنا المثنى بن عوف العنزي، بصري، قال: أنبأني الغضبان بن حنظلة:","english":{"narrator":"","text":""}},{"idInBook":61,"hadithNumber":142,"arabic":"حدثنا حسن بن موسى، حدثنا ابن لهيعة، قال: حدثنا يزيد بن أبي حبيب، عن معمر:","english":{"narrator":"","text":""},"grade":"Da'if"},{"idInBook":62,"hadithNumber":143,"arabic":"حدثنا أبو سعيد، حدثنا ديلم (3) بن غزوان، عبدي، حدثنا ميمون","english":{"narrator":"","text":""}},{"idInBook":63,"hadithNumber":144,"arabic":"حدثنا أبو سعيد، حدثنا عبد العزيز بن محمد، حدثنا صالح بن محمد بن زائدة","english":{"narrator":"","text":""},"grade":"Sahih"},{"idInBook":64,"hadithNumber":145,"arabic":"حدثنا أبو سعيد، وحسين بن محمد، قالا: حدثنا إسرائيل، عن أبي إسحاق، عن عمرو بن ميمون","english":{"narrator":"","text":""},"grade":"Da'if"},{"idInBook":65,"hadithNumber":146,"arabic":"حدثنا أبو سعيد (1) ، حدثنا ابن لهيعة، قال: سمعت عطاء بن دينار، عن أبي يزيد الخولاني، أنه سمع فضالة بن عبيد، يقول:","english":{"narrator":"","text":""},"grade":"Sahih"},{"idInBook":66,"hadithNumber":147,"arabic":"حدثنا أبو سعيد، حدثنا عبد الله بن لهيعة، حدثنا عمرو بن شعيب، عن أبيه، عن جده","english":{"narrator":"","text":""},"grade":"Da'if"},{"idInBook":67,"hadithNumber":148,"arabic":"حدثنا حسن، حدثنا ابن لهيعة، حدثنا عمرو بن شعيب، عن أبيه، عن عبد الله بن عمرو قال:","english":{"narrator":"","text":""},"grade":"Hasan"},{"idInBook":68,"hadithNumber":149,"arabic":"حدثنا حسن، حدثنا ابن لهيعة، حدثنا الضحاك بن شرحبيل، عن زيد بن أسلم، عن أبيه","english":{"narrator":"","text":""},"grade":"Hasan"},{"idInBook":69,"hadithNumber":150,"arabic":"حدثنا يحيى بن إسحاق، حدثنا ابن لهيعة، عن عطاء بن دينار، عن أبي يزيد الخولاني، قال: سمعت فضالة بن عبيد، يقول:","english":{"narrator":"","text":""},"grade":"Sahih"},{"idInBook":70,"hadithNumber":151,"arabic":"حدثنا يحيى بن غيلان، حدثنا رشدين بن سعد (2) ، حدثني أبو عبد الله الغافقي، عن زيد بن أسلم، عن أبيه","english":{"narrator":"","text":""},"grade":"Da'if"},{"idInBook":71,"hadithNumber":152,"arabic":"حدثنا حسن، حدثنا ابن لهيعة، حدثنا أبو الزبير، عن جابر","english":{"narrator":"","text":""},"grade":"Sahih"},{"idInBook":72,"hadithNumber":153,"arabic":"حدثنا الحسن، حدثنا ابن لهيعة، حدثنا أبو الزبير، عن جابر","english":{"narrator":"","text":""},"grade":"Da'if"},{"idInBook":73,"hadithNumber":154,"arabic":"حدثنا هشيم، قال: زعم الزهري، عن عبيد الله بن عبد الله بن عتبة بن مسعود، عن ابن عباس","english":{"narrator":"","text":""},"grade":"Sahih"},{"idInBook":74,"hadithNumber":155,"arabic":"حدثنا هشيم، أخبرنا أبو بشر، عن سعيد بن جبير","english":{"narrator":"","text":""},"grade":"Sahih"},{"idInBook":75,"hadithNumber":156,"arabic":"حدثنا هشيم، أخبرنا علي بن زيد، عن يوسف بن مهران، عن ابن عباس، قال:","english":{"narrator":"","text":""},"grade":"Sahih"},{"idInBook":76,"hadithNumber":157,"arabic":"حدثنا هشيم، أخبرنا حميد، عن أنس، قال:","english":{"narrator":"","text":""},"grade":"Da'if"},{"idInBook":77,"hadithNumber":158,"arabic":"حدثنا عبد الأعلى بن عبد الأعلى، عن معمر، عن الزهري، عن عروة بن الزبير، عن المسور بن مخرمة","english":{"narrator":"","text":""},"grade":"Sahih"},{"idInBook":78,"hadithNumber":159,"arabic":"حدثنا عمرو بن الهيثم، حدثنا شعبة، عن سماك بن حرب، عن النعمان بن بشير","english":{"narrator":"","text":""},"grade":"Sahih"},{"idInBook":79,"hadithNumber":160,"arabic":"حدثنا ابن أبي عدي، عن حميد، عن أنس، قال:","english":{"narrator":"","text":""},"grade":"Hasan"},{"idInBook":80,"hadithNumber":161,"arabic":"حدثنا الوليد بن مسلم، حدثنا الأوزاعي، أن يحيى بن أبي كثير حدثه عن عكرمة مولى ابن عباس، قال: سمعت ms0046 ابن عباس يقول:","english":{"narrator":"","text":""},"grade":"Sahih"},{"idInBook":81,"hadithNumber":162,"arabic":"حدثنا سفيان، عن الزهري، سمع مالك بن أوس بن الحدثان","english":{"narrator":"","text":""},"grade":"Sahih"},{"idInBook":82,"hadithNumber":163,"arabic":"حدثنا سفيان، عن الزهري، سمع أبا عبيد، قال:","english":{"narrator":"","text":""},"grade":"Sahih"},{"idInBook":83,"hadithNumber":164,"arabic":"حدثنا سفيان، عن الزهري، عن عبيد الله بن عبد الله بن عتبة، عن ابن عباس","english":{"narrator":"","text":""},"grade":"Sahih"},{"idInBook":84,"hadithNumber":165,"arabic":"حدثنا سفيان، عن عبد الله بن دينار، عن ابن عمر","english":{"narrator":"","text":""},"grade":"Sahih"},{"idInBook":85,"hadithNumber":166,"arabic":"حدثنا سفيان، عن زيد بن أسلم، عن أبيه:","english":{"narrator":"","text":""},"grade":"Sahih"},{"idInBook":86,"hadithNumber":167,"arabic":"حدثنا سفيان، عن عاصم بن عبيد الله، عن عبد الله بن عامر بن ربيعة، يحدث","english":{"narrator":"","text":""},"grade":"Sahih"},{"idInBook":87,"hadithNumber":168,"arabic":"حدثنا سفيان، عن يحيى، عن محمد بن إبراهيم التيمي، عن علقمة بن وقاص، قال:","english":{"narrator":"","text":""},"grade":"Sahih"},{"idInBook":88,"hadithNumber":169,"arabic":"حدثنا سفيان، عن عبدة بن أبي لبابة، عن أبي وائل، قال:","english":{"narrator":"","text":""},"grade":"Sahih"},{"idInBook":89,"hadithNumber":170,"arabic":"حدثنا سفيان، عن عمرو، عن طاوس، عن ابن عباس:","english":{"narrator":"","text":""},"grade":"Sahih"},{"idInBook":90,"hadithNumber":171,"arabic":"حدثنا سفيان، عن عمرو، ومعمر، عن الزهري، عن مالك بن أوس بن الحدثان","english":{"narrator":"","text":""},"grade":"Sahih"},{"idInBook":91,"hadithNumber":172,"arabic":"حدثنا سفيان، عن عمرو، عن الزهري، عن مالك بن أوس، قال:","english":{"narrator":"","text":""},"grade":"Sahih"},{"idInBook":92,"hadithNumber":173,"arabic":"حدثنا سفيان، عن ابن أبي يزيد (1) ، عن أبيه","english":{"narrator":"","text":""},"grade":"Sahih"},{"idInBook":93,"hadithNumber":174,"arabic":"حدثنا ابن إدريس، أخبرنا ابن جريج، عن ابن أبي عمار (1) ، عن عبد الله بن بابيه","english":{"narrator":"","text":""},"grade":"Sahih"},{"idInBook":94,"hadithNumber":175,"arabic":"حدثنا أبو معاوية، حدثنا الأعمش، عن إبراهيم، عن علقمة، قال:","english":{"narrator":"","text":""},"grade":"Sahih"},{"idInBook":95,"hadithNumber":176,"arabic":"حدثنا أبو معاوية، قال: حدثنا الأعمش، عن إبراهيم، عن عابس بن ربيعة، قال:","english":{"narrator":"","text":""}},{"idInBook":96,"hadithNumber":177,"arabic":"حدثنا جرير، عن عبد الملك بن عمير، عن جابر بن سمرة، قال:","english":{"narrator":"","text":""},"grade":"Sahih"},{"idInBook":97,"hadithNumber":178,"arabic":"حدثنا أبو معاوية، حدثنا الأعمش، عن إبراهيم، عن علقمة","english":{"narrator":"","text":""},"grade":"Sahih"},{"idInBook":98,"hadithNumber":179,"arabic":"حدثنا إسماعيل، عن سعيد بن أبي عروبة، عن قتادة، عن سالم بن","english":{"narrator":"","text":""},"grade":"Sahih"},{"idInBook":99,"hadithNumber":180,"arabic":"حدثنا يحيى، حدثنا شعبة، حدثنا قتادة، عن سعيد بن المسيب، عن ابن عمر","english":{"narrator":"","text":""},"grade":"Sahih"},{"idInBook":100,"hadithNumber":181,"arabic":"حدثنا يحيى، عن عبد الملك، حدثنا عبد الله مولى أسماء، قال:","english":{"narrator":"","text":""},"grade":"Sahih"},{"idInBook":101,"hadithNumber":182,"arabic":"حدثنا يحيى بن سعيد، أنا سألته، حدثنا سليمان بن المغيرة، حدثنا ثابت","english":{"narrator":"","text":""},"grade":"Sahih"},{"idInBook":102,"hadithNumber":183,"arabic":"حدثنا يحيى، حدثنا حسين المعلم، حدثنا عمرو بن شعيب، عن أبيه، عن جده، قال:","english":{"narrator":"","text":""},"grade":"Sahih"},{"idInBook":103,"hadithNumber":184,"arabic":"قرأت على يحيى بن سعيد: عثمان بن غياث، قال: حدثني","english":{"narrator":"","text":""},"grade":"Hasan"},{"idInBook":104,"hadithNumber":185,"arabic":"حدثنا يحيى، عن شعبة، حدثني سلمة بن كهيل، قال: سمعت أبا الحكم، قال:","english":{"narrator":"","text":""},"grade":"Sahih"},{"idInBook":105,"hadithNumber":186,"arabic":"حدثنا يحيى بن سعيد، أنا سألته، حدثنا هشام، ms0052 حدثنا (3) قتادة، عن","english":{"narrator":"","text":""},"grade":"Sahih"},{"idInBook":106,"hadithNumber":187,"arabic":"حدثنا عبد الله بن نمير، عن مجالد (3) ، عن عامر، عن جابر بن عبد الله، قال:","english":{"narrator":"","text":""},"grade":"Sahih"},{"idInBook":107,"hadithNumber":188,"arabic":"حدثنا جعفر بن عون، حدثنا (1) أبو عميس، عن قيس بن مسلم، عن طارق بن شهاب، قال:","english":{"narrator":"","text":""},"grade":"Sahih"},{"idInBook":108,"hadithNumber":189,"arabic":"حدثنا وكيع، حدثنا سفيان، عن عبد الرحمن بن الحارث بن عياش بن أبي ربيعة، عن حكيم بن حكيم بن عباد بن حنيف، عن أبي أمامة بن سهل بن حنيف:","english":{"narrator":"","text":""},"grade":"Sahih"},{"idInBook":109,"hadithNumber":190,"arabic":"حدثنا وكيع، حدثنا سفيان، عن أبي يعفور العبدي، قال: سمعت شيخا بمكة في إمارة الحجاج يحدث","english":{"narrator":"","text":""},"grade":"Hasan"},{"idInBook":110,"hadithNumber":191,"arabic":"حدثنا وكيع، حدثنا كهمس، عن ابن (1) بريدة، عن يحيى بن يعمر (2) ، عن ابن عمر:","english":{"narrator":"","text":""},"grade":"Hasan"},{"idInBook":111,"hadithNumber":192,"arabic":"حدثنا وكيع، حدثنا هشام بن عروة، عن أبيه (3) ، عن عاصم بن عمر","english":{"narrator":"","text":""},"grade":"Sahih"},{"idInBook":112,"hadithNumber":193,"arabic":"حدثنا يزيد، أخبرنا إسرائيل بن يونس، عن عبد الأعلى الثعلبي، عن عبد الرحمن بن أبي ليلى، قال:","english":{"narrator":"","text":""},"grade":"Sahih"},{"idInBook":113,"hadithNumber":194,"arabic":"حدثنا محمد بن جعفر، حدثنا سعيد، عن قتادة، عن سليمان، عن جابر بن عبد الله","english":{"narrator":"","text":""},"grade":"Da'if"},{"idInBook":114,"hadithNumber":195,"arabic":"حدثنا محمد بن جعفر، حدثنا شعبة، عن عاصم بن عبيد الله، عن سالم، عن عبد الله بن عمر","english":{"narrator":"","text":""},"grade":"Sahih"},{"idInBook":115,"hadithNumber":196,"arabic":"حدثنا محمد بن جعفر، حدثنا شعبة، وحجاج، قال: سمعت شعبة، عن عاصم بن عبيد الله، عن سالم، عن ابن عمر","english":{"narrator":"","text":""},"grade":"Da'if"},{"idInBook":116,"hadithNumber":197,"arabic":"حدثنا هشيم، أخبرنا الزهري، عن عبيد الله (1) بن عبد الله بن عتبة بن مسعود، أخبرني عبد الله بن عباس، حدثني عبد الرحمن بن عوف:","english":{"narrator":"","text":""},"grade":"Hasan"},{"idInBook":117,"hadithNumber":198,"arabic":"حدثنا محمد بن جعفر، حدثنا شعبة، قال: سمعت يزيد بن خمير يحدث، عن حبيب بن عبيد، عن جبير بن نفير","english":{"narrator":"","text":""},"grade":"Sahih"},{"idInBook":118,"hadithNumber":199,"arabic":"قرأت على عبد الرحمن بن مهدي: مالك، عن ابن شهاب، عن سالم بن عبد الله، عن ابن عمر، قال:","english":{"narrator":"","text":""},"grade":"Sahih"},{"idInBook":119,"hadithNumber":200,"arabic":"حدثنا عبد الرحمن، عن سفيان، عن أبي إسحاق، عن عمرو بن ميمون","english":{"narrator":"","text":""},"grade":"Sahih"},{"idInBook":120,"hadithNumber":201,"arabic":"حدثنا عبد الرزاق، أخبرنا ابن جريج، أخبرني أبو الزبير، أنه سمع جابر بن عبد الله، يقول:","english":{"narrator":"","text":""},"grade":"Sahih"},{"idInBook":121,"hadithNumber":202,"arabic":"حدثنا عبد الرزاق، حدثنا معمر، عن الزهري، عن سالم، عن أبيه:","english":{"narrator":"","text":""},"grade":"Sahih"},{"idInBook":122,"hadithNumber":203,"arabic":"حدثنا هاشم بن القاسم، حدثنا عكرمة - يعني ابن عمار - حدثني سماك الحنفي أبو زميل، قال: حدثني عبد الله بن عباس","english":{"narrator":"","text":""},"grade":"Sahih"},{"idInBook":123,"hadithNumber":204,"arabic":"حدثنا عبد الله بن يزيد، حدثنا داود - يعني ابن أبي الفرات - حدثني عبد الله بن بريدة (2)","english":{"narrator":"","text":""},"grade":"Hasan"},{"idInBook":124,"hadithNumber":205,"arabic":"حدثنا أبو عبد الرحمن، حدثنا حيوة، أخبرني بكر بن عمرو، أنه سمع عبد الله بن هبيرة، يقول: إنه سمع أبا تميم الجيشاني يقول:","english":{"narrator":"","text":""},"grade":"Sahih"},{"idInBook":125,"hadithNumber":206,"arabic":"حدثنا أبو عبد الرحمن، حدثني سعيد بن أبي أيوب (1) ، حدثني عطاء بن دينار، عن حكيم بن شريك الهذلي، عن يحيى بن ميمون الحضرمي، عن ربيعة الجرشي، عن أبي هريرة","english":{"narrator":"","text":""},"grade":"Sahih"},{"idInBook":126,"hadithNumber":207,"arabic":"حدثنا هاشم بن القاسم، حدثنا شعبة، عن يزيد بن خمير الهمداني أبي عمر (3) ، قال: سمعت حبيب بن عبيد، يحدث عن جبير بن نفير","english":{"narrator":"","text":""},"grade":"Da'if"},{"idInBook":127,"hadithNumber":208,"arabic":"حدثنا أبو نوح قراد، أخبرنا (1) عكرمة بن عمار، حدثنا سماك الحنفي أبو زميل، حدثني ابن عباس","english":{"narrator":"","text":""},"grade":"Sahih"},{"idInBook":128,"hadithNumber":209,"arabic":"حدثنا أبو نوح، حدثنا مالك بن أنس، عن زيد بن أسلم، عن أبيه","english":{"narrator":"","text":""},"grade":"Hasan"},{"idInBook":129,"hadithNumber":210,"arabic":"حدثنا أبو النضر، حدثنا المسعودي، عن حكيم بن جبير، عن موسى بن طلحة، عن ابن الحوتكية، قال:","english":{"narrator":"","text":""},"grade":"Sahih"},{"idInBook":130,"hadithNumber":211,"arabic":"حدثنا أبو النضر، حدثنا أبو عقيل، حدثنا مجالد بن سعيد، أخبرنا عامر","english":{"narrator":"","text":""},"grade":"Hasan"},{"idInBook":131,"hadithNumber":212,"arabic":"حدثنا إسحاق (3) بن عيسى، حدثنا ابن لهيعة، عن جعفر بن ربيعة، عن الزهري، عن محرر بن أبي هريرة، عن أبيه","english":{"narrator":"","text":""},"grade":"Da'if"},{"idInBook":132,"hadithNumber":213,"arabic":"حدثنا أبو عامر عبد الملك بن عمرو، قال: حدثنا هشام - يعني ابن سعد - عن زيد بن أسلم، عن أبيه، قال:","english":{"narrator":"","text":""},"grade":"Da'if"},{"idInBook":133,"hadithNumber":214,"arabic":"حدثنا محمد بن عبد الله الزبيري، حدثنا إسرائيل، عن سماك، عن عكرمة، عن ابن عباس","english":{"narrator":"","text":""},"grade":"Sahih"},{"idInBook":134,"hadithNumber":215,"arabic":"حدثنا أبو أحمد الزبيري، حدثنا سفيان، عن أبي الزبير، عن جابر","english":{"narrator":"","text":""},"grade":"Sahih"},{"idInBook":135,"hadithNumber":216,"arabic":"حدثنا سليمان بن داود أبو داود، حدثنا شريك، عن عاصم بن عبيد الله، عن أبيه","english":{"narrator":"","text":""},"grade":"Sahih"},{"idInBook":136,"hadithNumber":217,"arabic":"حدثنا سليمان بن داود أبو داود، حدثنا سلام - يعني أبا الأحوص - عن سماك بن حرب، عن سيار بن المعرور، قال:","english":{"narrator":"","text":""},"grade":"Sahih"},{"idInBook":137,"hadithNumber":218,"arabic":"قرأت على يحيى بن سعيد: زهير (4) ، قال: حدثنا أبو إسحاق، عن حارثة بن مضرب:","english":{"narrator":"","text":""},"grade":"Sahih"},{"idInBook":138,"hadithNumber":219,"arabic":"حدثنا روح ومؤمل، قالا: حدثنا سفيان الثوري، عن أبي الزبير، عن جابر بن عبد الله","english":{"narrator":"","text":""},"grade":"Sahih"},{"idInBook":139,"hadithNumber":220,"arabic":"حدثنا عتاب بن زياد، حدثنا عبد الله - يعني ابن المبارك - (4) أخبرنا يونس، عن الزهري، عن السائب بن يزيد وعبيد الله بن عبد الله بن عتبة، عن عبد الرحمن بن عبد","english":{"narrator":"","text":""},"grade":"Sahih"},{"idInBook":140,"hadithNumber":221,"arabic":"حدثنا أبو نوح قراد، حدثنا عكرمة بن عمار، حدثنا سماك الحنفي أبو زميل، حدثني ابن عباس","english":{"narrator":"","text":""},"grade":"Sahih"},{"idInBook":141,"hadithNumber":222,"arabic":"حدثنا عبد الرزاق، أخبرنا معمر، عن الزهري، عن عبيد الله بن عبد الله بن أبي ثور","english":{"narrator":"","text":""},"grade":"Hasan"},{"idInBook":142,"hadithNumber":223,"arabic":"حدثنا عبد الرزاق، ms0065 أخبرني يونس بن سليم، قال: أملى علي يونس بن يزيد الأيلي، عن ابن شهاب، عن عروة بن الزبير، عن عبد الرحمن بن عبد القاري:","english":{"narrator":"","text":""},"grade":"Sahih"},{"idInBook":143,"hadithNumber":224,"arabic":"حدثنا عبد الرزاق، أخبرنا معمر، عن الزهري، عن أبي عبيد مولى عبد الرحمن بن عوف:","english":{"narrator":"","text":""},"grade":"Da'if"},{"idInBook":144,"hadithNumber":225,"arabic":"حدثنا يعقوب، حدثنا أبي، عن محمد بن إسحاق، حدثني الزهري، عن سعد أبي عبيد (2) مولى عبد الرحمن بن أزهر، قال:","english":{"narrator":"","text":""},"grade":"Sahih"},{"idInBook":145,"hadithNumber":226,"arabic":"حدثنا عبد الرزاق، حدثنا عبد الله بن عمر، عن نافع، عن ابن عمر","english":{"narrator":"","text":""},"grade":"Hasan"},{"idInBook":146,"hadithNumber":227,"arabic":"حدثنا هشيم (1) ، أخبرني سيار، عن أبي وائل:","english":{"narrator":"","text":""},"grade":"Sahih"},{"idInBook":147,"hadithNumber":228,"arabic":"حدثنا أبو ms0066 معاوية، حدثنا الأعمش، عن إبراهيم، عن علقمة","english":{"narrator":"","text":""},"grade":"Sahih"},{"idInBook":148,"hadithNumber":229,"arabic":"حدثنا أبو معاوية، حدثنا عاصم الأحول، عن عبد الله بن سرجس، قال:","english":{"narrator":"","text":""},"grade":"Sahih"},{"idInBook":149,"hadithNumber":230,"arabic":"حدثنا عبد الله بن نمير، حدثنا عبيد الله، عن نافع، عن ابن عمر","english":{"narrator":"","text":""},"grade":"Sahih"},{"idInBook":150,"hadithNumber":231,"arabic":"حدثنا ابن نمير، أخبرنا هشام (4) ، عن أبيه، عن عاصم","english":{"narrator":"","text":""},"grade":"Sahih"},{"idInBook":151,"hadithNumber":232,"arabic":"حدثنا أبو كامل، حدثنا إبراهيم بن سعد، حدثنا ابن شهاب، (ح) وحدثنا عبد الرزاق، أخبرنا معمر، عن الزهري، المعنى، عن أبي الطفيل عامر بن واثلة:","english":{"narrator":"","text":""},"grade":"Sahih"},{"idInBook":152,"hadithNumber":233,"arabic":"حدثنا محمد بن فضيل، حدثنا إسماعيل بن سميع، عن مسلم البطين، عن أبي البختري، قال:","english":{"narrator":"","text":""}},{"idInBook":153,"hadithNumber":234,"arabic":"حدثنا عبد الرزاق، أخبرنا سفيان، عن الأعمش، عن شقيق بن سلمة، عن سلمان بن ms0067 ربيعة","english":{"narrator":"","text":""},"grade":"Da'if"},{"idInBook":154,"hadithNumber":235,"arabic":"حدثنا عبد الرزاق، أخبرنا عبيد الله بن عمر، عن نافع، عن ابن عمر","english":{"narrator":"","text":""},"grade":"Sahih"},{"idInBook":155,"hadithNumber":236,"arabic":"حدثنا عبد الرزاق، أخبرنا معمر، عن أيوب، عن نافع، عن ابن عمر:","english":{"narrator":"","text":""},"grade":"Sahih"},{"idInBook":156,"hadithNumber":237,"arabic":"حدثنا عبد الرزاق، أخبرنا عبيد الله بن عمر، عن نافع، قال:","english":{"narrator":"","text":""},"grade":"Sahih"},{"idInBook":157,"hadithNumber":238,"arabic":"حدثنا عبد الرزاق، أخبرنا معمر، عن الزهري، أخبرني مالك بن أوس بن الحدثان، قال:","english":{"narrator":"","text":""}},{"idInBook":158,"hadithNumber":239,"arabic":"حدثنا عبد الرزاق، حدثنا معمر، عن الزهري، عن عبيد الله بن عبد الله بن عتبة، قال:","english":{"narrator":"","text":""},"grade":"Sahih"},{"idInBook":159,"hadithNumber":240,"arabic":"حدثنا عبد الرزاق، أخبرنا إسرائيل، عن سماك، عن عكرمة، عن ابن عباس، قال:","english":{"narrator":"","text":""},"grade":"Sahih"},{"idInBook":160,"hadithNumber":241,"arabic":"حدثنا عبد الرزاق، حدثنا معمر، عن الزهري، عن سالم، عن أبيه","english":{"narrator":"","text":""},"grade":"Sahih"},{"idInBook":161,"hadithNumber":242,"arabic":"حدثنا خلف بن الوليد، حدثنا خالد، عن خالد، عن أبي عثمان","english":{"narrator":"","text":""},"grade":"Sahih"},{"idInBook":162,"hadithNumber":243,"arabic":"حدثنا يحيى بن سعيد، حدثنا التيمي، عن أبي عثمان، قال:","english":{"narrator":"","text":""},"grade":"Sahih"},{"idInBook":163,"hadithNumber":244,"arabic":"حدثنا يحيى، عن ابن جريج، حدثني عبد الرحمن بن عبد الله بن أبي عمار، عن عبد الله بن بابيه","english":{"narrator":"","text":""},"grade":"Sahih"},{"idInBook":164,"hadithNumber":245,"arabic":"حدثنا عبد الرزاق، أخبرنا ابن جريج، سمعت عبد الرحمن بن عبد الله بن أبي عمار يحدث، فذكره (1) .","english":{"narrator":"","text":""},"grade":"Sahih"},{"idInBook":165,"hadithNumber":246,"arabic":"حدثنا يحيى، عن ابن أبي عروبة، حدثنا قتادة، عن سعيد بن المسيب، قال:","english":{"narrator":"","text":""},"grade":"Sahih"},{"idInBook":166,"hadithNumber":247,"arabic":"حدثنا يحيى، حدثنا شعبة، حدثنا قتادة، عن سعيد بن المسيب، عن ابن عمر","english":{"narrator":"","text":""},"grade":"Hasan"},{"idInBook":167,"hadithNumber":248,"arabic":"حدثنا يحيى، عن عبيد الله، أخبرني نافع، عن ابن عمر","english":{"narrator":"","text":""},"grade":"Sahih"},{"idInBook":168,"hadithNumber":249,"arabic":"حدثنا يحيى (3) ، عن يحيى، قال: سمعت سعيد بن المسيب","english":{"narrator":"","text":""},"grade":"Sahih"},{"idInBook":169,"hadithNumber":250,"arabic":"حدثنا يحيى، حدثنا حميد، عن أنس، قال:","english":{"narrator":"","text":""},"grade":"Sahih"},{"idInBook":170,"hadithNumber":251,"arabic":"حدثنا يحيى، عن شعبة، حدثني أبو ذبيان","english":{"narrator":"","text":""},"grade":"Sahih"},{"idInBook":171,"hadithNumber":252,"arabic":"حدثنا يحيى، عن إسماعيل، حدثنا عامر، وحدثنا محمد بن عبيد، حدثنا إسماعيل بن أبي خالد، عن رجل، عن الشعبي، قال:","english":{"narrator":"","text":""},"grade":"Sahih"},{"idInBook":172,"hadithNumber":253,"arabic":"حدثنا يحيى، عن ابن جريج، حدثني سليمان بن عتيق، عن عبد الله بن بابيه","english":{"narrator":"","text":""},"grade":"Sahih"},{"idInBook":173,"hadithNumber":254,"arabic":"حدثنا يحيى، عن الأعمش، حدثنا شقيق","english":{"narrator":"","text":""},"grade":"Sahih"},{"idInBook":174,"hadithNumber":255,"arabic":"حدثنا يحيى، عن عبيد الله، حدثني نافع، عن ابن عمر","english":{"narrator":"","text":""},"grade":"Sahih"},{"idInBook":175,"hadithNumber":256,"arabic":"حدثنا عبد الرزاق، أخبرنا سفيان، عن منصور، عن أبي وائل","english":{"narrator":"","text":""},"grade":"Sahih"},{"idInBook":176,"hadithNumber":257,"arabic":"حدثنا وكيع، حدثنا سفيان، وعبد الرحمن، عن سفيان، عن زبيد الإيامي، عن عبد الرحمن بن أبي ليلى","english":{"narrator":"","text":""},"grade":"Sahih"},{"idInBook":177,"hadithNumber":258,"arabic":"حدثنا وكيع، حدثنا هشام بن سعد، عن زيد بن أسلم، عن أبيه","english":{"narrator":"","text":""},"grade":"Sahih"},{"idInBook":178,"hadithNumber":259,"arabic":"حدثنا وكيع، عن ابن أبي خالد، عن قيس، قال:","english":{"narrator":"","text":""},"grade":"Hasan"},{"idInBook":179,"hadithNumber":260,"arabic":"حدثنا مؤمل، حدثنا سفيان، عن سلمة، عن عمران السلمي، قال:","english":{"narrator":"","text":""},"grade":"Sahih"},{"idInBook":180,"hadithNumber":261,"arabic":"حدثنا أسود بن عامر، حدثنا حماد ms0072 بن سلمة، عن أبي سنان، عن عبيد بن آدم وأبي مريم وأبي شعيب:","english":{"narrator":"","text":""},"grade":"Sahih"},{"idInBook":181,"hadithNumber":262,"arabic":"حدثنا أبو نعيم، حدثنا مالك - يعني ابن مغول - قال: سمعت الفضيل بن عمرو، عن إبراهيم (3)","english":{"narrator":"","text":""},"grade":"Da'if"},{"idInBook":182,"hadithNumber":263,"arabic":"حدثنا أبو أحمد محمد بن عبد الله، حدثنا سفيان، عن عبد الله بن دينار، عن ابن عمر","english":{"narrator":"","text":""},"grade":"Sahih"},{"idInBook":183,"hadithNumber":264,"arabic":"حدثنا عفان، حدثنا همام، عن قتادة، عن قزعة (3) ، قال:","english":{"narrator":"","text":""},"grade":"Sahih"},{"idInBook":184,"hadithNumber":265,"arabic":"حدثنا عفان، حدثنا عبد الواحد بن زياد، حدثنا الحسن بن عبيد الله، حدثنا إبراهيم، عن علقمة، عن القرثع، عن قيس أو ابن قيس - رجل من جعفي -","english":{"narrator":"","text":""},"grade":"Sahih"},{"idInBook":185,"hadithNumber":266,"arabic":"حدثنا عفان، حدثنا حماد بن سلمة، عن سعيد الجريري، عن أبي نضرة، عن أسير بن جابر، قال:","english":{"narrator":"","text":""},"grade":"Sahih"},{"idInBook":186,"hadithNumber":268,"arabic":"حدثنا عفان، حدثنا حماد بن سلمة، حدثنا ثابت، عن أنس:","english":{"narrator":"","text":""},"grade":"Sahih"},{"idInBook":187,"hadithNumber":269,"arabic":"حدثنا عفان (3) ، حدثنا عبد الواحد، حدثنا يزيد الرشك، عن معاذة (4) ، عن أم عمرو ابنة عبد الله، أنها سمعت عبد الله بن الزبير يحدث","english":{"narrator":"","text":""},"grade":"Sahih"},{"idInBook":188,"hadithNumber":270,"arabic":"حدثنا عفان، حدثنا همام، حدثنا قتادة، حدثنا أبو العالية","english":{"narrator":"","text":""},"grade":"Sahih"},{"idInBook":189,"hadithNumber":271,"arabic":"حدثنا عفان، حدثنا أبان، حدثنا قتادة، عن أبي العالية","english":{"narrator":"","text":""},"grade":"Sahih"},{"idInBook":190,"hadithNumber":272,"arabic":"حدثنا عبد الرحمن، حدثنا سفيان، عن قيس بن مسلم، عن طارق بن شهاب:","english":{"narrator":"","text":""},"grade":"Sahih"},{"idInBook":191,"hadithNumber":273,"arabic":"حدثنا عبد الرحمن، حدثنا سفيان، عن قيس بن مسلم، عن طارق بن شهاب","english":{"narrator":"","text":""},"grade":"Sahih"},{"idInBook":192,"hadithNumber":274,"arabic":"حدثنا عبد الرحمن، عن سفيان، عن إبراهيم بن عبد الأعلى، عن سويد بن غفلة، قال:","english":{"narrator":"","text":""},"grade":"Sahih"},{"idInBook":193,"hadithNumber":275,"arabic":"حدثنا عبد الرحمن، عن سفيان. وعبد الرزاق، أخبرنا سفيان، عن أبي إسحاق (4) ، عن عمرو بن ميمون، قال:","english":{"narrator":"","text":""},"grade":"Sahih"},{"idInBook":194,"hadithNumber":276,"arabic":"حدثنا عبد الرحمن، حدثنا مالك، عن الزهري، عن عبيد الله بن عبد الله، عن ابن عباس، قال:","english":{"narrator":"","text":""},"grade":"Sahih"},{"idInBook":195,"hadithNumber":277,"arabic":"حدثنا عبد الرحمن، عن مالك، عن الزهري، عن عروة، عن عبد الرحمن بن عبد","english":{"narrator":"","text":""},"grade":"Sahih"},{"idInBook":196,"hadithNumber":278,"arabic":"حدثنا عبد الرزاق، أخبرنا معمر، عن الزهري، عن عروة، عن المسور بن مخرمة، وعبد الرحمن بن عبد القاري","english":{"narrator":"","text":""},"grade":"Sahih"},{"idInBook":197,"hadithNumber":279,"arabic":"حدثنا عبد الرحمن، حدثنا عبد الله بن المبارك، عن معمر، عن الزهري، عن السائب بن يزيد","english":{"narrator":"","text":""},"grade":"Sahih"},{"idInBook":198,"hadithNumber":280,"arabic":"حدثنا عبد الرزاق، حدثنا معمر، عن الزهري، عن السائب بن يزيد، قال:","english":{"narrator":"","text":""},"grade":"Sahih"},{"idInBook":199,"hadithNumber":281,"arabic":"حدثنا عبد الرحمن، عن مالك، عن زيد بن أسلم، عن أبيه","english":{"narrator":"","text":""},"grade":"Sahih"},{"idInBook":200,"hadithNumber":282,"arabic":"قرأت على عبد الرحمن: عن مالك، عن ابن شهاب، عن أبي عبيد مولى ابن ms0077 أزهر، أنه قال:","english":{"narrator":"","text":""},"grade":"Sahih"},{"idInBook":201,"hadithNumber":283,"arabic":"حدثنا إسماعيل بن (2) إبراهيم، عن يحيى بن أبي إسحاق، عن سالم بن عبد الله، قال:","english":{"narrator":"","text":""},"grade":"Sahih"},{"idInBook":202,"hadithNumber":284,"arabic":"حدثنا عبد الرحمن، عن مالك، عن زيد بن أسلم، عن أبيه","english":{"narrator":"","text":""},"grade":"Sahih"},{"idInBook":203,"hadithNumber":285,"arabic":"حدثنا إسماعيل، حدثنا سلمة بن علقمة، عن محمد بن سيرين، قال: نبئت عن أبي العجفاء السلمي، قال:","english":{"narrator":"","text":""},"grade":"Sahih"},{"idInBook":204,"hadithNumber":286,"arabic":"حدثنا إسماعيل، أخبرنا الجريري سعيد، عن أبي نضرة، عن أبي فراس، قال:","english":{"narrator":"","text":""},"grade":"Sahih"},{"idInBook":205,"hadithNumber":287,"arabic":"حدثنا إسماعيل مرة أخرى، أخبرنا سلمة بن علقمة، عن محمد بن سيرين، قال: نبئت عن أبي العجفاء، قال:","english":{"narrator":"","text":""},"grade":"Sahih"},{"idInBook":206,"hadithNumber":288,"arabic":"حدثنا إسماعيل، حدثنا أيوب، عن عبد الله بن أبي مليكة، قال:","english":{"narrator":"","text":""}},{"idInBook":207,"hadithNumber":289,"arabic":"حدثنا عبد الرزاق، أخبرنا ابن جريج، أخبرني عبد الله بن أبي مليكة ... فذكر معنى حديث أيوب إلا أنه قال:","english":{"narrator":"","text":""},"grade":"Sahih"},{"idInBook":208,"hadithNumber":290,"arabic":"حدثنا عبد الرزاق، أخبرنا ابن جريج، أخبرني عبد الله بن أبي مليكة، قال:","english":{"narrator":"","text":""},"grade":"Sahih"},{"idInBook":209,"hadithNumber":291,"arabic":"حدثنا حسين بن محمد، حدثنا إسرائيل، عن سماك، عن عكرمة، عن ابن عباس","english":{"narrator":"","text":""},"grade":"Sahih"},{"idInBook":210,"hadithNumber":292,"arabic":"حدثنا محمد بن ميسر أبو سعد الصاغاني، حدثنا محمد بن إسحاق، عن محمد بن عمرو بن عطاء، عن مالك بن أوس بن الحدثان، قال:","english":{"narrator":"","text":""},"grade":"Sahih"},{"idInBook":211,"hadithNumber":293,"arabic":"حدثنا عبد القدوس بن الحجاج، حدثنا صفوان، حدثني أبو المخارق زهير بن سالم","english":{"narrator":"","text":""},"grade":"Sahih"},{"idInBook":212,"hadithNumber":294,"arabic":"حدثنا يعقوب، حدثنا أبي، عن صالح، قال ابن شهاب: فقال سالم: فسمعت عبد الله بن عمر، يقول:","english":{"narrator":"","text":""},"grade":"Da'if"},{"idInBook":213,"hadithNumber":295,"arabic":"حدثنا عبد الرزاق، أخبرنا الثوري، عن أبي إسحاق، عن عمرو بن ميمون، قال:","english":{"narrator":"","text":""},"grade":"Da'if"},{"idInBook":214,"hadithNumber":296,"arabic":"حدثنا عبد الرزاق، أخبرنا معمر، عن الزهري، عن عروة، عن (2) المسور بن مخرمة، وعبد الرحمن بن عبد القاري","english":{"narrator":"","text":""},"grade":"Sahih"},{"idInBook":215,"hadithNumber":297,"arabic":"حدثنا الحكم بن نافع، أخبرنا شعيب، عن الزهري، حدثني عروة عن حديث المسور بن مخرمة وعبد الرحمن بن عبد القاري","english":{"narrator":"","text":""},"grade":"Sahih"},{"idInBook":216,"hadithNumber":298,"arabic":"حدثنا حسين بن علي، عن زائدة، عن عاصم، عن أبيه، عن ابن عباس، قال:","english":{"narrator":"","text":""},"grade":"Sahih"},{"idInBook":217,"hadithNumber":299,"arabic":"حدثنا محمد بن بشر، حدثنا هشام بن عروة، عن أبيه، عن ابن عمر:","english":{"narrator":"","text":""},"grade":"Sahih"},{"idInBook":218,"hadithNumber":300,"arabic":"حدثنا يزيد، أخبرنا يحيى بن سعيد، أن محمد بن إبراهيم أخبره، أنه سمع علقمة بن وقاص الليثي، يقول","english":{"narrator":"","text":""},"grade":"Sahih"},{"idInBook":219,"hadithNumber":301,"arabic":"حدثنا يزيد، أخبرنا عاصم، عن أبي عثمان النهدي","english":{"narrator":"","text":""},"grade":"Sahih"},{"idInBook":220,"hadithNumber":302,"arabic":"حدثنا يزيد، ms0083 أخبرنا يحيى، عن سعيد بن المسيب","english":{"narrator":"","text":""},"grade":"Sahih"},{"idInBook":221,"hadithNumber":303,"arabic":"حدثنا يزيد، أخبرنا العوام، حدثني شيخ كان مرابطا بالساحل، قال: لقيت أبا صالح مولى عمر بن الخطاب، فقال:","english":{"narrator":"","text":""},"grade":"Sahih"},{"idInBook":222,"hadithNumber":304,"arabic":"حدثنا يزيد، أخبرنا عبد الملك، عن أنس بن سيرين، قال:","english":{"narrator":"","text":""},"grade":"Sahih"},{"idInBook":223,"hadithNumber":305,"arabic":"حدثنا يزيد، أخبرنا أصبغ، عن أبي العلاء الشامي، قال:","english":{"narrator":"","text":""},"grade":"Da'if"},{"idInBook":224,"hadithNumber":306,"arabic":"حدثنا يزيد، أخبرنا محمد بن إسحاق، عن نافع، عن ابن عمر","english":{"narrator":"","text":""},"grade":"Sahih"},{"idInBook":225,"hadithNumber":307,"arabic":"حدثنا يزيد، أخبرنا ورقاء. ms0084 وأبو النضر، قال: حدثنا ورقاء، عن عبد الأعلى الثعلبي، عن عبد الرحمن بن أبي ليلى، قال:","english":{"narrator":"","text":""},"grade":"Da'if"},{"idInBook":226,"hadithNumber":308,"arabic":"حدثنا يزيد، أخبرنا جرير، أخبرنا الزبير بن الخريت (1) ، عن أبي لبيد (2) ، قال:","english":{"narrator":"","text":""},"grade":"Hasan"},{"idInBook":227,"hadithNumber":309,"arabic":"حدثنا يزيد، أخبرنا عاصم بن محمد، عن أبيه، عن ابن عمر","english":{"narrator":"","text":""},"grade":"Da'if"},{"idInBook":228,"hadithNumber":310,"arabic":"حدثنا يزيد، أخبرنا ديلم بن غزوان العبدي، حدثنا ميمون الكردي، عن أبي عثمان النهدي، قال:","english":{"narrator":"","text":""},"grade":"Da'if"},{"idInBook":229,"hadithNumber":312,"arabic":"حدثنا روح، حدثنا مالك بن أنس، عن ابن شهاب، عن سالم بن عبد الله بن عمر","english":{"narrator":"","text":""},"grade":"Sahih"},{"idInBook":230,"hadithNumber":313,"arabic":"حدثنا روح، حدثنا ابن جريج، أخبرني سليمان بن عتيق، عن عبد الله بن بابيه، عن بعض بني يعلى، عن يعلى بن أمية، قال:","english":{"narrator":"","text":""},"grade":"Sahih"},{"idInBook":231,"hadithNumber":314,"arabic":"حدثنا عثمان بن عمر، وأبو عامر، قالا: حدثنا مالك، عن الزهري","english":{"narrator":"","text":""},"grade":"Sahih"},{"idInBook":232,"hadithNumber":315,"arabic":"حدثنا عثمان بن عمر، أخبرنا يونس، عن الزهري، عن سعيد بن المسيب","english":{"narrator":"","text":""},"grade":"Sahih"},{"idInBook":233,"hadithNumber":316,"arabic":"حدثنا بكر بن عيسى، حدثنا أبو عوانة، عن المغيرة، عن الشعبي","english":{"narrator":"","text":""},"grade":"Sahih"},{"idInBook":234,"hadithNumber":317,"arabic":"حدثنا عبد الملك بن عمرو، حدثنا هشام بن سعد، عن زيد بن أسلم، عن أبيه، قال:","english":{"narrator":"","text":""},"grade":"Sahih"},{"idInBook":235,"hadithNumber":318,"arabic":"حدثنا عبد الصمد وعفان، قالا: حدثنا داود بن أبي الفرات، حدثنا عبد الله بن بريدة - قال ms0087 عفان: عن ابن بريدة -","english":{"narrator":"","text":""},"grade":"Sahih"},{"idInBook":236,"hadithNumber":319,"arabic":"حدثنا عبد الصمد، حدثنا حرب - يعني ابن شداد -، حدثنا يحيى، حدثنا أبو سلمة، حدثنا أبو هريرة، قال:","english":{"narrator":"","text":""},"grade":"Sahih"},{"idInBook":237,"hadithNumber":320,"arabic":"حدثنا عبد الصمد، حدثني أبي، حدثنا الحسين المعلم، حدثنا يحيى، أخبرني أبو سلمة (2) ، أن أبا هريرة أخبره:","english":{"narrator":"","text":""},"grade":"Sahih"},{"idInBook":238,"hadithNumber":321,"arabic":"حدثنا عبد الصمد، حدثنا حرب، حدثنا يحيى، عن عمران بن حطان (4) - فيما يحسب حرب -:","english":{"narrator":"","text":""},"grade":"Sahih"},{"idInBook":239,"hadithNumber":322,"arabic":"حدثنا يحيى بن حماد، وعفان، قالا: حدثنا أبو عوانة، عن داود بن عبد الله الأودي، عن حميد بن عبد الرحمن الحميري","english":{"narrator":"","text":""},"grade":"Sahih"},{"idInBook":240,"hadithNumber":323,"arabic":"حدثنا يحيى بن آدم، حدثنا سفيان، عن عبد الرحمن بن عياش، عن حكيم بن حكيم، عن أبي أمامة بن سهل، قال:","english":{"narrator":"","text":""},"grade":"Sahih"},{"idInBook":241,"hadithNumber":324,"arabic":"حدثنا عبد الله بن زيد، حدثنا ابن لهيعة، عن عمرو بن شعيب، عن أبيه، عن جده","english":{"narrator":"","text":""},"grade":"Sahih"},{"idInBook":242,"hadithNumber":325,"arabic":"حدثنا محمد بن عبيد، حدثنا الأعمش، عن إبراهيم، عن عابس بن ربيعة، قال:","english":{"narrator":"","text":""},"grade":"Sahih"},{"idInBook":243,"hadithNumber":326,"arabic":"حدثنا أبو سعيد، حدثنا دجين أبو الغصن، بصري، ms0089 قال:","english":{"narrator":"","text":""},"grade":"Hasan"},{"idInBook":244,"hadithNumber":327,"arabic":"حدثنا أبو سعيد، حدثنا حماد بن زيد، عن عمرو بن دينار مولى آل الزبير، عن سالم، عن أبيه","english":{"narrator":"","text":""},"grade":"Hasan"},{"idInBook":245,"hadithNumber":328,"arabic":"حدثنا أبو سعيد، حدثنا عكرمة بن عمار، حدثنا أبو زميل، حدثني ابن عباس","english":{"narrator":"","text":""},"grade":"Sahih"},{"idInBook":246,"hadithNumber":329,"arabic":"حدثنا أبو سعيد، حدثنا إسرائيل، حدثنا سعيد بن مسروق، عن","english":{"narrator":"","text":""},"grade":"Sahih"},{"idInBook":247,"hadithNumber":330,"arabic":"حدثنا حماد الخياط، حدثنا عبد الله، عن نافع:","english":{"narrator":"","text":""},"grade":"Da'if"},{"idInBook":248,"hadithNumber":331,"arabic":"حدثنا عبد الرزاق، حدثنا معمر، عن الزهري، عن عبيد الله بن عبد الله بن عتبة ms0090 بن مسعود، عن ابن عباس","english":{"narrator":"","text":""},"grade":"Hasan"},{"idInBook":249,"hadithNumber":332,"arabic":"حدثنا عبد الرزاق، حدثنا معمر، عن الزهري، عن سالم","english":{"narrator":"","text":""},"grade":"Sahih"},{"idInBook":250,"hadithNumber":333,"arabic":"حدثنا عبد الرزاق، حدثنا معمر، عن الزهري، عن مالك بن أوس بن الحدثان، قال:","english":{"narrator":"","text":""},"grade":"Da'if"},{"idInBook":251,"hadithNumber":334,"arabic":"حدثنا عبد الرزاق، حدثنا معمر، عن الزهري، عن ابن المسيب، قال:","english":{"narrator":"","text":""},"grade":"Sahih"},{"idInBook":252,"hadithNumber":335,"arabic":"حدثنا إبراهيم بن خالد، حدثنا رباح، عن معمر، عن الزهري، عن عبيد الله بن عبد الله بن عتبة، عن أبي هريرة، قال:","english":{"narrator":"","text":""},"grade":"Sahih"},{"idInBook":253,"hadithNumber":336,"arabic":"حدثنا سفيان، عن عمرو، عن الزهري، عن مالك بن أوس","english":{"narrator":"","text":""},"grade":"Sahih"},{"idInBook":254,"hadithNumber":337,"arabic":"حدثنا سفيان، عن عمرو، عن الزهري، عن مالك بن أوس، قال:","english":{"narrator":"","text":""},"grade":"Sahih"},{"idInBook":255,"hadithNumber":338,"arabic":"حدثنا سفيان، عن هشام، عن أبيه، عن عاصم بن عمر","english":{"narrator":"","text":""},"grade":"Sahih"},{"idInBook":256,"hadithNumber":339,"arabic":"حدثنا سفيان، عن يحيى - يعني ابن سعيد - عن عبيد بن حنين (3)","english":{"narrator":"","text":""},"grade":"Sahih"},{"idInBook":257,"hadithNumber":340,"arabic":"حدثنا سفيان، عن أيوب، عن ابن سيرين، سمعه (1) من أبي العجفاء","english":{"narrator":"","text":""},"grade":"Sahih"},{"idInBook":258,"hadithNumber":341,"arabic":"حدثنا محمد بن جعفر، حدثنا سعيد بن أبي عروبة، أمله علي، عن قتادة، عن سالم بن أبي الجعد الغطفاني، عن معدان بن أبي طلحة اليعمري:","english":{"narrator":"","text":""},"grade":"Sahih"},{"idInBook":259,"hadithNumber":342,"arabic":"حدثنا عبد الرزاق. قال (2) : وأخبرني هشيم، عن الحجاج بن أرطاة، عن الحكم بن عتيبة، عن عمارة، عن أبي بردة، عن أبي موسى","english":{"narrator":"","text":""},"grade":"Sahih"},{"idInBook":260,"hadithNumber":343,"arabic":"حدثنا علي بن عاصم، أخبرنا يزيد بن أبي زياد، عن عاصم بن عبيد الله، عن أبيه، أو جده - الشك من يزيد -","english":{"narrator":"","text":""},"grade":"Sahih"},{"idInBook":261,"hadithNumber":344,"arabic":"حدثنا محمد بن جعفر، حدثنا شعبة، عن سماك، قال:","english":{"narrator":"","text":""},"grade":"Sahih"},{"idInBook":262,"hadithNumber":345,"arabic":"حدثنا محمد بن بكر، أخبرنا عيينة، عن علي بن زيد، قال:","english":{"narrator":"","text":""},"grade":"Sahih"},{"idInBook":263,"hadithNumber":346,"arabic":"حدثنا ms0094 أبو المنذر أسد بن عمرو، أراه عن حجاج، عن عمرو بن شعيب، عن أبيه، عن جده، قال:","english":{"narrator":"","text":""},"grade":"Sahih"},{"idInBook":264,"hadithNumber":347,"arabic":"حدثنا هشيم ويزيد، عن يحيى بن سعيد، عن عمرو بن شعيب، قال:","english":{"narrator":"","text":""},"grade":"Hasan"},{"idInBook":265,"hadithNumber":348,"arabic":"حدثنا يعقوب، حدثنا أبي، عن ابن إسحاق، حدثني عبد الله بن أبي نجيح وعمرو بن شعيب، كلاهما عن مجاهد بن جبر، فذكر الحديث، وقال:","english":{"narrator":"","text":""},"grade":"Sahih"},{"idInBook":266,"hadithNumber":349,"arabic":"حدثنا إسماعيل، حدثنا أيوب، عن عكرمة بن خالد، عن مالك بن أوس بن الحدثان قال:","english":{"narrator":"","text":""},"grade":"Hasan"},{"idInBook":267,"hadithNumber":350,"arabic":"حدثنا إسماعيل، عن ابن أبي عروبة، عن قتادة، عن ابن المسيب","english":{"narrator":"","text":""},"grade":"Hasan"},{"idInBook":268,"hadithNumber":351,"arabic":"حدثنا أبو عبد الله محمد بن جعفر، حدثنا شعبة، عن الحكم، عن عمارة بن عمير، عن إبراهيم بن أبي موسى","english":{"narrator":"","text":""},"grade":"Hasan"},{"idInBook":269,"hadithNumber":352,"arabic":"حدثنا محمد بن جعفر وحجاج، قالا: حدثنا شعبة، عن سعد بن إبراهيم، قال: سمعت عبيد الله بن عبد الله بن عتبة يحدث عن ابن عباس، عن عبد الرحمن بن عوف، قال:","english":{"narrator":"","text":""},"grade":"Sahih"},{"idInBook":270,"hadithNumber":353,"arabic":"حدثنا محمد بن جعفر وحجاج، قالا: حدثنا شعبة، عن سماك بن حرب، قال: سمعت النعمان - يعني ابن بشير - يخطب قال:","english":{"narrator":"","text":""},"grade":"Hasan"},{"idInBook":271,"hadithNumber":354,"arabic":"حدثنا محمد بن جعفر، حدثنا شعبة. وحجاج، قال: حدثني شعبة، قال: سمعت قتادة يحدث عن سعيد بن المسيب، عن ابن عمر","english":{"narrator":"","text":""},"grade":"Sahih"},{"idInBook":272,"hadithNumber":355,"arabic":"حدثنا محمد بن جعفر، حدثنا شعبة، عن قتادة، قال: سمعت رفيعا (2) أبا العالية يحدث","english":{"narrator":"","text":""},"grade":"Sahih"},{"idInBook":273,"hadithNumber":356,"arabic":"حدثنا محمد بن جعفر، حدثنا شعبة. وحجاج، قال: حدثني شعبة،","english":{"narrator":"","text":""},"grade":"Hasan"},{"idInBook":274,"hadithNumber":357,"arabic":"حدثنا محمد بن جعفر، حدثنا شعبة. وحجاج وأبو داود، قال: حدثني شعبة، عن قتادة قال: سمعت أبا عثمان النهدي قال: جاءنا كتاب عمر (2) .","english":{"narrator":"","text":""},"grade":"Sahih"},{"idInBook":275,"hadithNumber":358,"arabic":"حدثنا محمد بن جعفر، حدثنا شعبة. وأبو داود، عن شعبة، عن أبي إسحاق، عن عمرو بن ميمون، قال:","english":{"narrator":"","text":""},"grade":"Sahih"},{"idInBook":276,"hadithNumber":359,"arabic":"حدثنا محمد بن جعفر، حدثنا شعبة، عن عبد الله (1) بن دينار، قال: سمعت ابن عمر يقول:","english":{"narrator":"","text":""},"grade":"Sahih"},{"idInBook":277,"hadithNumber":360,"arabic":"حدثنا محمد بن جعفر، حدثنا شعبة، عن سلمة بن كهيل، قال: سمعت أبا الحكم قال:","english":{"narrator":"","text":""},"grade":"Sahih"},{"idInBook":278,"hadithNumber":361,"arabic":"حدثنا محمد بن جعفر، حدثنا شعبة، عن عاصم الأحول، عن عبد الله بن سرجس، قال:","english":{"narrator":"","text":""},"grade":"Sahih"},{"idInBook":279,"hadithNumber":362,"arabic":"حدثنا محمد بن جعفر، حدثنا شعبة، قال: سمعت أبا جمرة الضبعي، يحدث عن جويرية بن قدامة، قال:","english":{"narrator":"","text":""},"grade":"Sahih"},{"idInBook":280,"hadithNumber":363,"arabic":"حدثنا حجاج، أخبرنا شعبة، سمعت أبا جمرة الضبعي يحدث عن جويرية بن قدامة، قال:","english":{"narrator":"","text":""},"grade":"Sahih"},{"idInBook":281,"hadithNumber":364,"arabic":"حدثنا محمد بن جعفر، حدثنا سعيد، وعبد الوهاب، عن سعيد (3) ،","english":{"narrator":"","text":""},"grade":"Sahih"},{"idInBook":282,"hadithNumber":365,"arabic":"حدثنا محمد بن جعفر، حدثنا سعيد، عن قتادة، عن الشعبي، عن سويد بن غفلة:","english":{"narrator":"","text":""},"grade":"Sahih"},{"idInBook":283,"hadithNumber":366,"arabic":"حدثنا محمد بن جعفر، حدثنا سعيد، عن قتادة، عن سعيد بن المسيب، عن ابن عمر","english":{"narrator":"","text":""},"grade":"Sahih"},{"idInBook":284,"hadithNumber":367,"arabic":"حدثنا محمد بن جعفر، حدثنا كهمس، عن ابن بريدة. ويزيد بن هارون، قال: حدثنا كهمس، عن ابن بريدة، عن يحيى بن يعمر، سمع ابن عمر، قال:","english":{"narrator":"","text":""},"grade":"Sahih"},{"idInBook":285,"hadithNumber":368,"arabic":"حدثنا عبد الله بن يزيد، حدثنا كهمس، عن عبد الله بن بريدة، عن يحيى بن يعمر، سمع ابن عمر، قال:","english":{"narrator":"","text":""},"grade":"Sahih"},{"idInBook":286,"hadithNumber":369,"arabic":"حدثنا بهز. قال (1) : وحدثنا عفان، قالا: حدثنا همام، حدثنا قتادة، عن أبي نضرة، قال:","english":{"narrator":"","text":""},"grade":"Sahih"},{"idInBook":287,"hadithNumber":370,"arabic":"حدثنا حجاج، أخبرنا ابن لهيعة، عن عبد الله بن هبيرة، عن أبي تميم","english":{"narrator":"","text":""},"grade":"Sahih"},{"idInBook":288,"hadithNumber":371,"arabic":"حدثنا حجاج، حدثنا ليث، حدثني بكير بن عبد الله، عن بسر بن سعيد","english":{"narrator":"","text":""},"grade":"Sahih"},{"idInBook":289,"hadithNumber":372,"arabic":"حدثنا حجاج، حدثنا ليث، حدثني بكير، عن عبد الملك بن سعيد الأنصاري، عن جابر بن عبد الله","english":{"narrator":"","text":""},"grade":"Sahih"},{"idInBook":290,"hadithNumber":373,"arabic":"حدثنا يحيى بن إسحاق، أخبرنا ابن لهيعة، حدثنا عبد الله بن هبيرة، قال: سمعت أبا تميم الجيشاني يقول:","english":{"narrator":"","text":""},"grade":"Sahih"},{"idInBook":291,"hadithNumber":374,"arabic":"حدثنا أبو نعيم، حدثنا سفيان، عن علقمة بن مرثد، عن سليمان بن ms0100 بريدة، عن ابن يعمر، قال:","english":{"narrator":"","text":""},"grade":"Sahih"},{"idInBook":292,"hadithNumber":375,"arabic":"حدثنا أبو أحمد، حدثنا سفيان، عن علقمة بن مرثد، عن سليمان بن بريدة، عن ابن يعمر قال:","english":{"narrator":"","text":""},"grade":"Sahih"},{"idInBook":293,"hadithNumber":376,"arabic":"حدثنا حسن بن موسى الأشيب، حدثنا ابن لهيعة، حدثنا الوليد بن أبي الوليد، عن عثمان بن عبد الله بن سراقة العدوي","english":{"narrator":"","text":""},"grade":"Sahih"},{"idInBook":294,"hadithNumber":377,"arabic":"حدثنا عتاب - يعني ابن زياد - حدثنا عبد الله - يعني ابن المبارك - أخبرنا يونس، عن الزهري، عن السائب بن يزيد وعبيد الله بن عبد الله بن عتبة، عن عبد الرحمن بن عبد","english":{"narrator":"","text":""},"grade":"Sahih"},{"idInBook":295,"hadithNumber":378,"arabic":"حدثنا خلف بن الوليد، حدثنا إسرائيل، عن أبي إسحاق، عن أبي ميسرة","english":{"narrator":"","text":""},"grade":"Sahih"},{"idInBook":296,"hadithNumber":379,"arabic":"حدثنا عفان، حدثنا شعبة، عن الحكم، عن أبي وائل","english":{"narrator":"","text":""},"grade":"Sahih"},{"idInBook":297,"hadithNumber":380,"arabic":"حدثنا يحيى بن سعيد، عن هشام، قال: أخبرني أبي","english":{"narrator":"","text":""},"grade":"Sahih"},{"idInBook":298,"hadithNumber":381,"arabic":"حدثنا وكيع، عن هشام، عن أبيه","english":{"narrator":"","text":""},"grade":"Sahih"},{"idInBook":299,"hadithNumber":382,"arabic":"حدثنا وكيع، حدثنا سفيان، عن إبراهيم بن عبد الأعلى، عن سويد بن غفلة:","english":{"narrator":"","text":""},"grade":"Sahih"},{"idInBook":300,"hadithNumber":383,"arabic":"حدثنا وكيع، حدثنا هشام بن عروة، عن أبيه، عن عاصم بن عمر","english":{"narrator":"","text":""},"grade":"Sahih"},{"idInBook":301,"hadithNumber":384,"arabic":"حدثنا وكيع، حدثنا هشام بن سعد، عن زيد بن أسلم، عن أبيه","english":{"narrator":"","text":""},"grade":"Sahih"},{"idInBook":302,"hadithNumber":385,"arabic":"حدثنا وكيع، عن سفيان، عن أبي إسحاق، عن عمرو بن ميمون","english":{"narrator":"","text":""},"grade":"Sahih"},{"idInBook":303,"hadithNumber":386,"arabic":"حدثنا وكيع، حدثنا رباح بن أبي معروف، عن ابن أبي مليكة، سمع ابن عباس:","english":{"narrator":"","text":""},"grade":"Sahih"},{"idInBook":304,"hadithNumber":387,"arabic":"حدثنا وكيع، عن حسن بن صالح، عن عاصم بن عبيد الله، عن سالم، عن ابن عمر، قال:","english":{"narrator":"","text":""},"grade":"Hasan"},{"idInBook":305,"hadithNumber":388,"arabic":"حدثنا وكيع، عن إسرائيل، عن أبي إسحاق، عن عمرو بن ميمون","english":{"narrator":"","text":""},"grade":"Sahih"},{"idInBook":306,"hadithNumber":389,"arabic":"حدثنا وكيع، حدثني عمر بن الوليد الشني، عن عبد الله بن بريدة، قال:","english":{"narrator":"","text":""},"grade":"Hasan"},{"idInBook":307,"hadithNumber":390,"arabic":"حدثنا عبد الرحمن، حدثنا سفيان، عن أبيه، عن عباية بن رفاعة، قال:","english":{"narrator":"","text":""},"grade":"Sahih"},{"idInBook":308,"hadithNumber":391,"arabic":"حدثنا إسحاق بن عيسى الطباع، حدثنا مالك بن أنس، حدثني ابن شهاب، عن عبيد الله بن عبد الله بن عتبة بن مسعود","english":{"narrator":"","text":""},"grade":"Sahih"},{"idInBook":309,"hadithNumber":392,"arabic":"حدثنا إسحاق بن عيسى، أخبرني مالك، عن يحيى بن سعيد","english":{"narrator":"","text":""},"grade":"Sahih"},{"idInBook":310,"hadithNumber":393,"arabic":"حدثنا إسحاق بن عيسى، حدثنا مالك، عن نافع","english":{"narrator":"","text":""}},{"idInBook":311,"hadithNumber":394,"arabic":"حدثنا إسحاق بن عيسى، أخبرنا مالك، عن نافع","english":{"narrator":"","text":""},"grade":"Sahih"},{"idInBook":312,"hadithNumber":395,"arabic":"حدثنا إسحاق بن عيسى، أخبرنا مالك، عن نافع","english":{"narrator":"","text":""},"grade":"Sahih"},{"idInBook":313,"hadithNumber":396,"arabic":"حدثنا إسحاق بن عيسى، أخبرنا مالك، عن نافع","english":{"narrator":"","text":""},"grade":"Sahih"},{"idInBook":314,"hadithNumber":397,"arabic":"حدثنا إسحاق بن عيسى، أخبرنا مالك، ms0108 عن نافع","english":{"narrator":"","text":""},"grade":"Sahih"},{"idInBook":315,"hadithNumber":398,"arabic":"حدثنا سفيان، عن أيوب، عن سعيد، قال:","english":{"narrator":"","text":""},"grade":"Sahih"}]