[{"idInBook":1,"hadithNumber":16411,"arabic":"حدثنا وكيع، حدثنا سفيان، عن زيد بن أسلم، عن عطاء بن يسار، عن رجل من بني أسد قال: قال رسول الله صلى الله عليه وسلم: \" من سأل وله أوقية أو عدلها فقد سأل إلحافا \" (1)","english":{"narrator":"","text":""}},{"idInBook":2,"hadithNumber":23648,"arabic":"حدثنا عبد الرحمن بن مهدي، عن سفيان، عن زيد بن أسلم، عن عطاء بن يسار، عن رجل من بني أسد، عن النبي صلى الله عليه وسلم قال: \" لا يسأل رجل وله أوقية أو عدلها، إلا سأل إلحافا \" (1)","english":{"narrator":"","text":""}}]