[{"idInBook":1,"hadithNumber":18726,"arabic":"حدثنا محمد بن جعفر، حدثنا شعبة، عن معبد بن خالد، قال: سمعت حارثة بن وهب قال: سمعت رسول الله صلى الله عليه وسلم يقول: \" تصدقوا، فيوشك الرجل يمشي بصدقته فيقول: الذي أعطيها لو جئت بها بالأمس، قبلتها، وأما الآن، فلا حاجة لي فيها، فلا يجد من يقبلها \" (2)","english":{"narrator":"","text":""},"grade":"Sahih"},{"idInBook":2,"hadithNumber":18727,"arabic":"حدثنا وكيع، حدثنا سفيان، عن أبي إسحاق، عن حارثة بن وهب الخزاعي قال: \" صليت مع النبي صلى الله عليه وسلم الظهر أو العصر (1) بمنى، أكثر ما كان الناس، وآمنه ركعتين \" (2)","english":{"narrator":"","text":""},"grade":"Sahih"},{"idInBook":3,"hadithNumber":18728,"arabic":"حدثنا وكيع، عن سفيان، عن معبد بن خالد، قال: سمعت حارثة بن وهب الخزاعي يقول: قال رسول الله صلى الله عليه وسلم: \" ألا أخبركم بأهل الجنة؟ كل ضعيف متضعف لو يقسم (1) على الله، لأبره. ألا أخبركم بأهل النار؟ كل جواظ جعظري مستكبر \" (2)","english":{"narrator":"","text":""},"grade":"Sahih"},{"idInBook":4,"hadithNumber":18729,"arabic":"حدثنا وكيع، عن شعبة، عن معبد بن خالد،","english":{"narrator":"","text":""}},{"idInBook":5,"hadithNumber":18730,"arabic":"حدثنا عبد الرحمن بن مهدي، عن سفيان، عن معبد بن خالد، عن حارثة بن وهب قال: قال رسول الله صلى الله عليه وسلم: \" ألا أنبئكم بأهل الجنة؟ كل ضعيف متضعف لو أقسم على الله لأبره. ألا أنبئكم بأهل النار؟ كل عتل ms3537 جواظ مستكبر \" (2)","english":{"narrator":"","text":""},"grade":"Sahih"},{"idInBook":6,"hadithNumber":18731,"arabic":"حدثنا محمد بن جعفر، حدثنا شعبة، قال: سمعت أبا إسحاق يحدث، عن حارثة بن وهب الخزاعي قال: \" صلى بنا رسول الله صلى الله عليه وسلم أكثر ما كنا، وآمنه بمنى ركعتين \"، (3)","english":{"narrator":"","text":""}},{"idInBook":7,"hadithNumber":18732,"arabic":"حدثنا أبو نعيم، حدثنا سفيان، عن معبد بن خالد قال: سمعت حارثة بن وهب الخزاعي قال: سمعت رسول الله صلى الله عليه وسلم، فذكر الحديث (1)","english":{"narrator":"","text":""},"grade":"Da'if"}]