[{"idInBook":1,"hadithNumber":23480,"arabic":"حدثنا حسن، حدثنا ابن لهيعة، حدثنا يزيد بن عمرو المعافري، عن رجل من بني غفار، أن رسول الله صلى الله عليه وسلم قال: \" من لم يحلق عانته، ويقلم أظفاره، ويجز شاربه فليس منا \" (1)","english":{"narrator":"","text":""},"grade":"Sahih"},{"idInBook":2,"hadithNumber":23686,"arabic":"حدثنا يزيد، أخبرنا إبراهيم بن سعد، أخبرني أبي، قال: كنت جالسا إلى جنب حميد بن عبد الرحمن في المسجد، فمر شيخ جميل من بني غفار وفي أذنيه صمم، أو قال: وقر، أرسل إليه حميد، فلما أقبل قال: يا ابن أخي، أوسع له فيما بيني وبينك، فإنه قد صحب رسول الله صلى الله عليه وسلم فجاء حتى جلس فيما بيني وبينه، فقال له حميد: حدثني بالحديث (1) الذي حدثتني عن رسول الله صلى الله عليه وسلم فقال الشيخ: سمعت رسول الله صلى الله عليه وسلم يقول: \" إن الله ينشئ السحاب، فينطق أحسن المنطق، ويضحك أحسن الضحك \" (2)","english":{"narrator":"","text":""},"grade":"Sahih"},{"idInBook":3,"hadithNumber":23687,"arabic":"حدثنا روح، حدثنا الأوزاعي، عن عبد الله بن سعد، عن الصنابحي، عن رجل، من أصحاب النبي صلى ms4586 الله عليه وسلم قال: \" نهى رسول الله صلى الله عليه وسلم عن الغلوطات \" قال الأوزاعي: الغلوطات: شداد المسائل وصعابها (1)","english":{"narrator":"","text":""},"grade":"Sahih"},{"idInBook":4,"hadithNumber":23688,"arabic":"حدثنا علي بن بحر، حدثنا عيسى بن يونس، حدثنا الأوزاعى، عن عبد الله بن سعد، عن الصنابحي، عن معاوية، عن النبي صلى الله عليه وسلم أنه: \" نهى عن الغلوطات \" (1)","english":{"narrator":"","text":""},"grade":"Sahih"}]