[{"idInBook":1,"hadithNumber":27449,"arabic":"حدثنا روح، أخبرنا مالك بن أنس، عن زيد بن أسلم، عن عمرو بن معاذ الأشهلي، عن ms5344 جدته، أنها قالت: قال رسول الله صلى الله عليه وسلم: \" يا نساء المؤمنات لا تحقرن إحداكن لجارتها، ولو كراع شاة محرق \" (2)","english":{"narrator":"","text":""},"grade":"Sahih"},{"idInBook":2,"hadithNumber":27450,"arabic":"حدثنا روح، أخبرنا مالك، عن زيد بن أسلم، عن ابن بجيد الأنصاري، عن جدته، أن رسول الله صلى الله عليه وسلم قال: \" ردوا السائل ولو بظلف","english":{"narrator":"","text":""},"grade":"Sahih"},{"idInBook":3,"hadithNumber":27451,"arabic":"حدثنا عبد الملك بن عمرو، حدثنا زهير بن محمد، عن زيد، عن عمرو بن معاذ الأنصاري، قال: إن سائلا وقف على بابهم (2) فقالت له جدته حواء أطعموه","english":{"narrator":"","text":""},"grade":"Sahih"}]